app.py
pyconsole_portable-0.1.0.dist-info/METADATA
pyconsole_portable-0.1.0.dist-info/WHEEL
pyconsole_portable-0.1.0.dist-info/top_level.txt
pyconsole_portable-0.1.0.dist-info/RECORD
