Metadata-Version: 2.4
Name: pyconsole-portable
Version: 0.1.0
Summary: Self-contained Python app with urllib3 HTTP requests
Author-email: PyConsole Team <team@pyconsole.dev>
License: MIT
Project-URL: Homepage, https://github.com/karlorz/pyconsole
Project-URL: Repository, https://github.com/karlorz/pyconsole
Project-URL: Documentation, https://github.com/karlorz/pyconsole#readme
Project-URL: Issues, https://github.com/karlorz/pyconsole/issues
Keywords: python,packaging,deployment,portable
Classifier: Development Status :: 4 - Beta
Classifier: Intended Audience :: Developers
Classifier: Programming Language :: Python :: 3
Classifier: Programming Language :: Python :: 3.8
Classifier: Programming Language :: Python :: 3.9
Classifier: Programming Language :: Python :: 3.10
Classifier: Programming Language :: Python :: 3.11
Classifier: Programming Language :: Python :: 3.12
Requires-Python: >=3.8
Requires-Dist: urllib3>=2.0.0
